README.txt
setup.py
docs/HISTORY.txt
docs/INSTALL.txt
docs/LICENSE.GPL
docs/LICENSE.txt
plone/__init__.py
plone.pony.egg-info/PKG-INFO
plone.pony.egg-info/SOURCES.txt
plone.pony.egg-info/dependency_links.txt
plone.pony.egg-info/namespace_packages.txt
plone.pony.egg-info/not-zip-safe
plone.pony.egg-info/requires.txt
plone.pony.egg-info/top_level.txt
plone/pony/README.txt
plone/pony/__init__.py
plone/pony/configure.zcml
plone/pony/interfaces.py
plone/pony/pony.pt
plone/pony/tests.py
plone/pony/profiles/default/browserlayer.xml
plone/pony/profiles/default/cssregistry.xml
plone/pony/profiles/default/metadata.xml
plone/pony/profiles/default/viewlets.xml
plone/pony/resources/main.css