Metadata-Version: 1.0
Name: plone.pony
Version: 1.1
Summary: A pony for Plone.
Home-page: http://svn.plone.org/svn/plone/plone.pony
Author: Plone Foundation
Author-email: plone-developers@lists.sourceforge.net
License: GPL
Download-URL: http://cheeseshop.python.org/pypi/plone.pony/
Keywords: plone pony
Platform: Any
Classifier: Development Status :: 5 - Production/Stable
Classifier: Environment :: Web Environment
Classifier: Framework :: Plone
Classifier: Intended Audience :: System Administrators
Classifier: Intended Audience :: Other Audience
Classifier: License :: OSI Approved :: GNU General Public License (GPL)
Classifier: Operating System :: OS Independent
Classifier: Programming Language :: Python
Classifier: Topic :: Software Development :: Libraries :: Python Modules
